Workbook

Sheet FRV_Scope
A1: report_id | B1: CAP_NR | C1: Capability | D1: SABI_1 | E1: SABI_2 | F1: EDWH_1 | G1: EDWH_2 | H1: EDWH_3 | I1: EDWH_4 | J1: OU | K1: Directie | L1: Start | M1: End
A2: RAP10033 | B2: 24 | C2: CAP - 24. data & analytics | J2: =IFERROR(VLOOKUP(A2,Directie!$A:$B,2,FALSE),"") -> CLP | K2: =IFERROR(VLOOKUP(A2,Directie!$A:$C,3,FALSE),"") -> SC | L2: 46174 | M2: 46569
A3: RAP10033 | B3: 16 | C3: CAP - 16. direct purchasing | D3: Ivan Zelic | E3: Veera Raghavi Anusha Kakarlapudi | F3: Alan Eykmans | J3: =IFERROR(VLOOKUP(A3,Directie!$A:$B,2,FALSE),"") -> CLP | K3: =IFERROR(VLOOKUP(A3,Directie!$A:$C,3,FALSE),"") -> SC | L3: 46174 | M3: 46569
A4: RAP10033 | B4: 44 | C4: CAP - 44. Store Sales Food | J4: =IFERROR(VLOOKUP(A4,Directie!$A:$B,2,FALSE),"") -> CLP | K4: =IFERROR(VLOOKUP(A4,Directie!$A:$C,3,FALSE),"") -> SC | L4: 46174 | M4: 46569
A5: RAP10033 | B5: 40 | C5: CAP - 40. Retail Product Information | F5: Alan Eykmans | J5: =IFERROR(VLOOKUP(A5,Directie!$A:$B,2,FALSE),"") -> CLP | K5: =IFERROR(VLOOKUP(A5,Directie!$A:$C,3,FALSE),"") -> SC | L5: 46174 | M5: 46569
A6: RAP10033 | B6: 31 | C6: CAP - 31. Infrastructure | D6: Stefan Van Theemsche | F6: Naga Venkata Vamshi Krishna Rao Kanaparthi | J6: =IFERROR(VLOOKUP(A6,Directie!$A:$B,2,FALSE),"") -> CLP | K6: =IFERROR(VLOOKUP(A6,Directie!$A:$C,3,FALSE),"") -> SC | L6: 46174 | M6: 46569
A7: RAP10033 | B7: 71 | C7: CAP - 71. B2C sales food | D7: Christiaan Fosselle | J7: =IFERROR(VLOOKUP(A7,Directie!$A:$B,2,FALSE),"") -> CLP | K7: =IFERROR(VLOOKUP(A7,Directie!$A:$C,3,FALSE),"") -> SC | L7: 46174 | M7: 46569
A8: RAP10034 | B8: 24 | C8: CAP - 24. data & analytics | J8: =IFERROR(VLOOKUP(A8,Directie!$A:$B,2,FALSE),"") -> CLP | K8: =IFERROR(VLOOKUP(A8,Directie!$A:$C,3,FALSE),"") -> SC | L8: 46174 | M8: 46569
A9: RAP10034 | B9: 16 | C9: CAP - 16. direct purchasing | D9: Ivan Zelic | E9: Veera Raghavi Anusha Kakarlapudi | F9: Alan Eykmans | J9: =IFERROR(VLOOKUP(A9,Directie!$A:$B,2,FALSE),"") -> CLP | K9: =IFERROR(VLOOKUP(A9,Directie!$A:$C,3,FALSE),"") -> SC | L9: 46174 | M9: 46569
A10: RAP10034 | B10: 44 | C10: CAP - 44. Store Sales Food | J10: =IFERROR(VLOOKUP(A10,Directie!$A:$B,2,FALSE),"") -> CLP | K10: =IFERROR(VLOOKUP(A10,Directie!$A:$C,3,FALSE),"") -> SC | L10: 46174 | M10: 46569
A11: RAP10034 | B11: 40 | C11: CAP - 40. Retail Product Information | F11: Alan Eykmans | J11: =IFERROR(VLOOKUP(A11,Directie!$A:$B,2,FALSE),"") -> CLP | K11: =IFERROR(VLOOKUP(A11,Directie!$A:$C,3,FALSE),"") -> SC | L11: 46174 | M11: 46569
A12: RAP10034 | B12: 71 | C12: CAP - 71. B2C sales food | D12: Christiaan Fosselle | J12: =IFERROR(VLOOKUP(A12,Directie!$A:$B,2,FALSE),"") -> CLP | K12: =IFERROR(VLOOKUP(A12,Directie!$A:$C,3,FALSE),"") -> SC | L12: 46174 | M12: 46569
A13: RAP10073 | B13: 24 | C13: CAP - 24. data & analytics | J13: =IFERROR(VLOOKUP(A13,Directie!$A:$B,2,FALSE),"") -> CLP | K13: =IFERROR(VLOOKUP(A13,Directie!$A:$C,3,FALSE),"") -> Verkoop | L13: 46174 | M13: 46419
A14: RAP10073 | B14: 47 | C14: CAP - 47. supply chain food | D14: Mustapha Guilmi | E14: Neelam Swamy | F14: Naga Venkata Vamshi Krishna Rao Kanaparthi | G14: SriHarsha Siddam | J14: =IFERROR(VLOOKUP(A14,Directie!$A:$B,2,FALSE),"") -> CLP | K14: =IFERROR(VLOOKUP(A14,Directie!$A:$C,3,FALSE),"") -> Verkoop | L14: 46174 | M14: 46419
A15: RAP10073 | B15: 30 | C15: CAP - 30. it | D15: Nithish Srivathsava Chittampally | E15: Stefan Van Theemsche | J15: =IFERROR(VLOOKUP(A15,Directie!$A:$B,2,FALSE),"") -> CLP | K15: =IFERROR(VLOOKUP(A15,Directie!$A:$C,3,FALSE),"") -> Verkoop | L15: 46174 | M15: 46419
A16: RAP10073 | B16: 44 | C16: CAP - 44. Store Sales Food | J16: =IFERROR(VLOOKUP(A16,Directie!$A:$B,2,FALSE),"") -> CLP | K16: =IFERROR(VLOOKUP(A16,Directie!$A:$C,3,FALSE),"") -> Verkoop | L16: 46174 | M16: 46419
A17: RAP10073 | B17: 40 | C17: CAP - 40. Retail Product Information | F17: Alan Eykmans | J17: =IFERROR(VLOOKUP(A17,Directie!$A:$B,2,FALSE),"") -> CLP | K17: =IFERROR(VLOOKUP(A17,Directie!$A:$C,3,FALSE),"") -> Verkoop | L17: 46174 | M17: 46419
A18: RAP1033 | B18: 24 | C18: CAP - 24. data & analytics | J18: =IFERROR(VLOOKUP(A18,Directie!$A:$B,2,FALSE),"") -> CLP | K18: =IFERROR(VLOOKUP(A18,Directie!$A:$C,3,FALSE),"") -> SC | L18: 46174 | M18: 46569
A19: RAP1033 | B19: 47 | C19: CAP - 47. supply chain food | D19: Mustapha Guilmi | E19: Neelam Swamy | F19: Naga Venkata Vamshi Krishna Rao Kanaparthi | G19: SriHarsha Siddam | J19: =IFERROR(VLOOKUP(A19,Directie!$A:$B,2,FALSE),"") -> CLP | K19: =IFERROR(VLOOKUP(A19,Directie!$A:$C,3,FALSE),"") -> SC | L19: 46174 | M19: 46569
A20: RAP1036 | J20: =IFERROR(VLOOKUP(A20,Directie!$A:$B,2,FALSE),"") -> CLP | K20: =IFERROR(VLOOKUP(A20,Directie!$A:$C,3,FALSE),"") -> SC | L20: 46174 | M20: 46569
A21: RAP1036 | B21: 47 | C21: CAP - 47. supply chain food | D21: Mustapha Guilmi | E21: Neelam Swamy | F21: Naga Venkata Vamshi Krishna Rao Kanaparthi | G21: SriHarsha Siddam | J21: =IFERROR(VLOOKUP(A21,Directie!$A:$B,2,FALSE),"") -> CLP | K21: =IFERROR(VLOOKUP(A21,Directie!$A:$C,3,FALSE),"") -> SC | L21: 46174 | M21: 46569
A22: RAP1036 | B22: 40 | C22: CAP - 40. Retail Product Information | F22: Alan Eykmans | J22: =IFERROR(VLOOKUP(A22,Directie!$A:$B,2,FALSE),"") -> CLP | K22: =IFERROR(VLOOKUP(A22,Directie!$A:$C,3,FALSE),"") -> SC | L22: 46174 | M22: 46569
A23: RAP10413 | B23: 44 | C23: CAP - 44. Store Sales Food | J23: =IFERROR(VLOOKUP(A23,Directie!$A:$B,2,FALSE),"") -> BIO | K23: =IFERROR(VLOOKUP(A23,Directie!$A:$C,3,FALSE),"") -> CO | L23: 46327 | M23: 46600
A24: RAP10413 | B24: 31 | C24: CAP - 31. Infrastructure | D24: Stefan Van Theemsche | F24: Naga Venkata Vamshi Krishna Rao Kanaparthi | J24: =IFERROR(VLOOKUP(A24,Directie!$A:$B,2,FALSE),"") -> BIO | K24: =IFERROR(VLOOKUP(A24,Directie!$A:$C,3,FALSE),"") -> CO | L24: 46327 | M24: 46600
A25: RAP10413 | B25: 37 | C25: CAP - 37. co-worker | D25: Swetha Kotturi | E25: Stefan Van Theemsche | J25: =IFERROR(VLOOKUP(A25,Directie!$A:$B,2,FALSE),"") -> BIO | K25: =IFERROR(VLOOKUP(A25,Directie!$A:$C,3,FALSE),"") -> CO | L25: 46327 | M25: 46600
A26: RAP10553 | B26: 32 | C26: CAP - 32. finance | D26: Nithish Srivathsava Chittampally | E26: Stefan Van Theemsche | J26: =IFERROR(VLOOKUP(A26,Directie!$A:$B,2,FALSE),"") -> CLP | K26: =IFERROR(VLOOKUP(A26,Directie!$A:$C,3,FALSE),"") -> Verkoop | L26: 46174 | M26: 46419
A27: RAP10553 | B27: 24 | C27: CAP - 24. data & analytics | J27: =IFERROR(VLOOKUP(A27,Directie!$A:$B,2,FALSE),"") -> CLP | K27: =IFERROR(VLOOKUP(A27,Directie!$A:$C,3,FALSE),"") -> Verkoop | L27: 46174 | M27: 46419
A28: RAP10553 | B28: 16 | C28: CAP - 16. direct purchasing | D28: Ivan Zelic | E28: Veera Raghavi Anusha Kakarlapudi | F28: Alan Eykmans | J28: =IFERROR(VLOOKUP(A28,Directie!$A:$B,2,FALSE),"") -> CLP | K28: =IFERROR(VLOOKUP(A28,Directie!$A:$C,3,FALSE),"") -> Verkoop | L28: 46174 | M28: 46419
A29: RAP10553 | B29: 18 | C29: CAP - 18. customer | D29: Dimitri Vanlinthout | F29: Dimitri Vanlinthout | G29: Kevin Kollin Mathew | H29: Ajay Mannepalli | I29: Dona Eliza Joseph | J29: =IFERROR(VLOOKUP(A29,Directie!$A:$B,2,FALSE),"") -> CLP | K29: =IFERROR(VLOOKUP(A29,Directie!$A:$C,3,FALSE),"") -> Verkoop | L29: 46174 | M29: 46419
A30: RAP10553 | B30: 44 | C30: CAP - 44. Store Sales Food | J30: =IFERROR(VLOOKUP(A30,Directie!$A:$B,2,FALSE),"") -> CLP | K30: =IFERROR(VLOOKUP(A30,Directie!$A:$C,3,FALSE),"") -> Verkoop | L30: 46174 | M30: 46419
A31: RAP10553 | B31: 40 | C31: CAP - 40. Retail Product Information | F31: Alan Eykmans | J31: =IFERROR(VLOOKUP(A31,Directie!$A:$B,2,FALSE),"") -> CLP | K31: =IFERROR(VLOOKUP(A31,Directie!$A:$C,3,FALSE),"") -> Verkoop | L31: 46174 | M31: 46419
A32: RAP10553 | B32: 71 | C32: CAP - 71. B2C sales food | D32: Christiaan Fosselle | J32: =IFERROR(VLOOKUP(A32,Directie!$A:$B,2,FALSE),"") -> CLP | K32: =IFERROR(VLOOKUP(A32,Directie!$A:$C,3,FALSE),"") -> Verkoop | L32: 46174 | M32: 46419
A33: RAP1091 | B33: 24 | C33: CAP - 24. data & analytics | J33: =IFERROR(VLOOKUP(A33,Directie!$A:$B,2,FALSE),"") -> CLP | K33: =IFERROR(VLOOKUP(A33,Directie!$A:$C,3,FALSE),"") -> SC | L33: 46174 | M33: 46569
A34: RAP1091 | B34: 16 | C34: CAP - 16. direct purchasing | D34: Ivan Zelic | E34: Veera Raghavi Anusha Kakarlapudi | F34: Alan Eykmans | J34: =IFERROR(VLOOKUP(A34,Directie!$A:$B,2,FALSE),"") -> CLP | K34: =IFERROR(VLOOKUP(A34,Directie!$A:$C,3,FALSE),"") -> SC | L34: 46174 | M34: 46569
A35: RAP1091 | B35: 47 | C35: CAP - 47. supply chain food | D35: Mustapha Guilmi | E35: Neelam Swamy | F35: Naga Venkata Vamshi Krishna Rao Kanaparthi | G35: SriHarsha Siddam | J35: =IFERROR(VLOOKUP(A35,Directie!$A:$B,2,FALSE),"") -> CLP | K35: =IFERROR(VLOOKUP(A35,Directie!$A:$C,3,FALSE),"") -> SC | L35: 46174 | M35: 46569
A36: RAP1091 | B36: 18 | C36: CAP - 18. customer | D36: Dimitri Vanlinthout | F36: Dimitri Vanlinthout | G36: Kevin Kollin Mathew | H36: Ajay Mannepalli | I36: Dona Eliza Joseph | J36: =IFERROR(VLOOKUP(A36,Directie!$A:$B,2,FALSE),"") -> CLP | K36: =IFERROR(VLOOKUP(A36,Directie!$A:$C,3,FALSE),"") -> SC | L36: 46174 | M36: 46569
A37: RAP1091 | B37: 40 | C37: CAP - 40. Retail Product Information | F37: Alan Eykmans | J37: =IFERROR(VLOOKUP(A37,Directie!$A:$B,2,FALSE),"") -> CLP | K37: =IFERROR(VLOOKUP(A37,Directie!$A:$C,3,FALSE),"") -> SC | L37: 46174 | M37: 46569
A38: RAP10915 | B38: 24 | C38: CAP - 24. data & analytics | J38: =IFERROR(VLOOKUP(A38,Directie!$A:$B,2,FALSE),"") -> CLP | K38: =IFERROR(VLOOKUP(A38,Directie!$A:$C,3,FALSE),"") -> SC | L38: 46174 | M38: 46569
A39: RAP10915 | B39: 47 | C39: CAP - 47. supply chain food | D39: Mustapha Guilmi | E39: Neelam Swamy | F39: Naga Venkata Vamshi Krishna Rao Kanaparthi | G39: SriHarsha Siddam | J39: =IFERROR(VLOOKUP(A39,Directie!$A:$B,2,FALSE),"") -> CLP | K39: =IFERROR(VLOOKUP(A39,Directie!$A:$C,3,FALSE),"") -> SC | L39: 46174 | M39: 46569
A40: RAP10915 | B40: 37 | C40: CAP - 37. co-worker | D40: Swetha Kotturi | E40: Stefan Van Theemsche | J40: =IFERROR(VLOOKUP(A40,Directie!$A:$B,2,FALSE),"") -> CLP | K40: =IFERROR(VLOOKUP(A40,Directie!$A:$C,3,FALSE),"") -> SC | L40: 46174 | M40: 46569
A41: RAP11014 | J41: =IFERROR(VLOOKUP(A41,Directie!$A:$B,2,FALSE),"") -> CLP | K41: =IFERROR(VLOOKUP(A41,Directie!$A:$C,3,FALSE),"") -> SC | L41: 46174 | M41: 46569
A42: RAP11093 | B42: 32 | C42: CAP - 32. finance | D42: Nithish Srivathsava Chittampally | E42: Stefan Van Theemsche | J42: =IFERROR(VLOOKUP(A42,Directie!$A:$B,2,FALSE),"") -> CLP | K42: =IFERROR(VLOOKUP(A42,Directie!$A:$C,3,FALSE),"") -> Verkoop | L42: 46174 | M42: 46419
A43: RAP11093 | B43: 18 | C43: CAP - 18. customer | D43: Dimitri Vanlinthout | F43: Dimitri Vanlinthout | G43: Kevin Kollin Mathew | H43: Ajay Mannepalli | I43: Dona Eliza Joseph | J43: =IFERROR(VLOOKUP(A43,Directie!$A:$B,2,FALSE),"") -> CLP | K43: =IFERROR(VLOOKUP(A43,Directie!$A:$C,3,FALSE),"") -> Verkoop | L43: 46174 | M43: 46419
A44: RAP11093 | B44: 44 | C44: CAP - 44. Store Sales Food | J44: =IFERROR(VLOOKUP(A44,Directie!$A:$B,2,FALSE),"") -> CLP | K44: =IFERROR(VLOOKUP(A44,Directie!$A:$C,3,FALSE),"") -> Verkoop | L44: 46174 | M44: 46419
A45: RAP11093 | B45: 31 | C45: CAP - 31. Infrastructure | D45: Stefan Van Theemsche | F45: Naga Venkata Vamshi Krishna Rao Kanaparthi | J45: =IFERROR(VLOOKUP(A45,Directie!$A:$B,2,FALSE),"") -> CLP | K45: =IFERROR(VLOOKUP(A45,Directie!$A:$C,3,FALSE),"") -> Verkoop | L45: 46174 | M45: 46419
A46: RAP11093 | B46: 37 | C46: CAP - 37. co-worker | D46: Swetha Kotturi | E46: Stefan Van Theemsche | J46: =IFERROR(VLOOKUP(A46,Directie!$A:$B,2,FALSE),"") -> CLP | K46: =IFERROR(VLOOKUP(A46,Directie!$A:$C,3,FALSE),"") -> Verkoop | L46: 46174 | M46: 46419
A47: RAP1164 | B47: 24 | C47: CAP - 24. data & analytics | J47: =IFERROR(VLOOKUP(A47,Directie!$A:$B,2,FALSE),"") -> CLP | K47: =IFERROR(VLOOKUP(A47,Directie!$A:$C,3,FALSE),"") -> SC | L47: 46174 | M47: 46569
A48: RAP1164 | B48: 47 | C48: CAP - 47. supply chain food | D48: Mustapha Guilmi | E48: Neelam Swamy | F48: Naga Venkata Vamshi Krishna Rao Kanaparthi | G48: SriHarsha Siddam | J48: =IFERROR(VLOOKUP(A48,Directie!$A:$B,2,FALSE),"") -> CLP | K48: =IFERROR(VLOOKUP(A48,Directie!$A:$C,3,FALSE),"") -> SC | L48: 46174 | M48: 46569
A49: RAP1164 | B49: 40 | C49: CAP - 40. Retail Product Information | F49: Alan Eykmans | J49: =IFERROR(VLOOKUP(A49,Directie!$A:$B,2,FALSE),"") -> CLP | K49: =IFERROR(VLOOKUP(A49,Directie!$A:$C,3,FALSE),"") -> SC | L49: 46174 | M49: 46569
A50: RAP1165 | J50: =IFERROR(VLOOKUP(A50,Directie!$A:$B,2,FALSE),"") -> CLP | K50: =IFERROR(VLOOKUP(A50,Directie!$A:$C,3,FALSE),"") -> SC | L50: 46174 | M50: 46569
A51: RAP1165 | B51: 24 | C51: CAP - 24. data & analytics | J51: =IFERROR(VLOOKUP(A51,Directie!$A:$B,2,FALSE),"") -> CLP | K51: =IFERROR(VLOOKUP(A51,Directie!$A:$C,3,FALSE),"") -> SC | L51: 46174 | M51: 46569
A52: RAP1165 | B52: 16 | C52: CAP - 16. direct purchasing | D52: Ivan Zelic | E52: Veera Raghavi Anusha Kakarlapudi | F52: Alan Eykmans | J52: =IFERROR(VLOOKUP(A52,Directie!$A:$B,2,FALSE),"") -> CLP | K52: =IFERROR(VLOOKUP(A52,Directie!$A:$C,3,FALSE),"") -> SC | L52: 46174 | M52: 46569
A53: RAP1165 | B53: 47 | C53: CAP - 47. supply chain food | D53: Mustapha Guilmi | E53: Neelam Swamy | F53: Naga Venkata Vamshi Krishna Rao Kanaparthi | G53: SriHarsha Siddam | J53: =IFERROR(VLOOKUP(A53,Directie!$A:$B,2,FALSE),"") -> CLP | K53: =IFERROR(VLOOKUP(A53,Directie!$A:$C,3,FALSE),"") -> SC | L53: 46174 | M53: 46569
A54: RAP1165 | B54: 40 | C54: CAP - 40. Retail Product Information | F54: Alan Eykmans | J54: =IFERROR(VLOOKUP(A54,Directie!$A:$B,2,FALSE),"") -> CLP | K54: =IFERROR(VLOOKUP(A54,Directie!$A:$C,3,FALSE),"") -> SC | L54: 46174 | M54: 46569
A55: RAP1165 | B55: 20 | C55: CAP - 20. business partner | D55: Ivan Zelic | E55: Veera Raghavi Anusha Kakarlapudi | F55: Alan Eykmans | J55: =IFERROR(VLOOKUP(A55,Directie!$A:$B,2,FALSE),"") -> CLP | K55: =IFERROR(VLOOKUP(A55,Directie!$A:$C,3,FALSE),"") -> SC | L55: 46174 | M55: 46569
A56: RAP1170 | B56: 47 | C56: CAP - 47. supply chain food | D56: Mustapha Guilmi | E56: Neelam Swamy | F56: Naga Venkata Vamshi Krishna Rao Kanaparthi | G56: SriHarsha Siddam | J56: =IFERROR(VLOOKUP(A56,Directie!$A:$B,2,FALSE),"") -> CLP | K56: =IFERROR(VLOOKUP(A56,Directie!$A:$C,3,FALSE),"") -> SC | L56: 46174 | M56: 46569
A57: RAP1170 | B57: 44 | C57: CAP - 44. Store Sales Food | J57: =IFERROR(VLOOKUP(A57,Directie!$A:$B,2,FALSE),"") -> CLP | K57: =IFERROR(VLOOKUP(A57,Directie!$A:$C,3,FALSE),"") -> SC | L57: 46174 | M57: 46569
A58: RAP1170 | B58: 40 | C58: CAP - 40. Retail Product Information | F58: Alan Eykmans | J58: =IFERROR(VLOOKUP(A58,Directie!$A:$B,2,FALSE),"") -> CLP | K58: =IFERROR(VLOOKUP(A58,Directie!$A:$C,3,FALSE),"") -> SC | L58: 46174 | M58: 46569
A59: RAP1171 | B59: 47 | C59: CAP - 47. supply chain food | D59: Mustapha Guilmi | E59: Neelam Swamy | F59: Naga Venkata Vamshi Krishna Rao Kanaparthi | G59: SriHarsha Siddam | J59: =IFERROR(VLOOKUP(A59,Directie!$A:$B,2,FALSE),"") -> CLP | K59: =IFERROR(VLOOKUP(A59,Directie!$A:$C,3,FALSE),"") -> SC | L59: 46174 | M59: 46569
A60: RAP1171 | B60: 44 | C60: CAP - 44. Store Sales Food | J60: =IFERROR(VLOOKUP(A60,Directie!$A:$B,2,FALSE),"") -> CLP | K60: =IFERROR(VLOOKUP(A60,Directie!$A:$C,3,FALSE),"") -> SC | L60: 46174 | M60: 46569
A61: RAP1171 | B61: 40 | C61: CAP - 40. Retail Product Information | F61: Alan Eykmans | J61: =IFERROR(VLOOKUP(A61,Directie!$A:$B,2,FALSE),"") -> CLP | K61: =IFERROR(VLOOKUP(A61,Directie!$A:$C,3,FALSE),"") -> SC | L61: 46174 | M61: 46569
A62: RAP1171 | B62: 20 | C62: CAP - 20. business partner | D62: Ivan Zelic | E62: Veera Raghavi Anusha Kakarlapudi | F62: Alan Eykmans | J62: =IFERROR(VLOOKUP(A62,Directie!$A:$B,2,FALSE),"") -> CLP | K62: =IFERROR(VLOOKUP(A62,Directie!$A:$C,3,FALSE),"") -> SC | L62: 46174 | M62: 46569
A63: RAP1173 | B63: 47 | C63: CAP - 47. supply chain food | D63: Mustapha Guilmi | E63: Neelam Swamy | F63: Naga Venkata Vamshi Krishna Rao Kanaparthi | G63: SriHarsha Siddam | J63: =IFERROR(VLOOKUP(A63,Directie!$A:$B,2,FALSE),"") -> CLP | K63: =IFERROR(VLOOKUP(A63,Directie!$A:$C,3,FALSE),"") -> SC | L63: 46174 | M63: 46569
A64: RAP1173 | B64: 44 | C64: CAP - 44. Store Sales Food | J64: =IFERROR(VLOOKUP(A64,Directie!$A:$B,2,FALSE),"") -> CLP | K64: =IFERROR(VLOOKUP(A64,Directie!$A:$C,3,FALSE),"") -> SC | L64: 46174 | M64: 46569
A65: RAP1173 | B65: 40 | C65: CAP - 40. Retail Product Information | F65: Alan Eykmans | J65: =IFERROR(VLOOKUP(A65,Directie!$A:$B,2,FALSE),"") -> CLP | K65: =IFERROR(VLOOKUP(A65,Directie!$A:$C,3,FALSE),"") -> SC | L65: 46174 | M65: 46569
A66: RAP1177 | B66: 47 | C66: CAP - 47. supply chain food | D66: Mustapha Guilmi | E66: Neelam Swamy | F66: Naga Venkata Vamshi Krishna Rao Kanaparthi | G66: SriHarsha Siddam | J66: =IFERROR(VLOOKUP(A66,Directie!$A:$B,2,FALSE),"") -> CLP | K66: =IFERROR(VLOOKUP(A66,Directie!$A:$C,3,FALSE),"") -> SC | L66: 46174 | M66: 46569
A67: RAP1177 | B67: 40 | C67: CAP - 40. Retail Product Information | F67: Alan Eykmans | J67: =IFERROR(VLOOKUP(A67,Directie!$A:$B,2,FALSE),"") -> CLP | K67: =IFERROR(VLOOKUP(A67,Directie!$A:$C,3,FALSE),"") -> SC | L67: 46174 | M67: 46569
A68: RAP11796 | J68: =IFERROR(VLOOKUP(A68,Directie!$A:$B,2,FALSE),"") -> CLP | K68: =IFERROR(VLOOKUP(A68,Directie!$A:$C,3,FALSE),"") -> SC | L68: 46174 | M68: 46569
A69: RAP1180 | B69: 47 | C69: CAP - 47. supply chain food | D69: Mustapha Guilmi | E69: Neelam Swamy | F69: Naga Venkata Vamshi Krishna Rao Kanaparthi | G69: SriHarsha Siddam | J69: =IFERROR(VLOOKUP(A69,Directie!$A:$B,2,FALSE),"") -> CLP | K69: =IFERROR(VLOOKUP(A69,Directie!$A:$C,3,FALSE),"") -> SC | L69: 46174 | M69: 46569
A70: RAP1180 | B70: 40 | C70: CAP - 40. Retail Product Information | F70: Alan Eykmans | J70: =IFERROR(VLOOKUP(A70,Directie!$A:$B,2,FALSE),"") -> CLP | K70: =IFERROR(VLOOKUP(A70,Directie!$A:$C,3,FALSE),"") -> SC | L70: 46174 | M70: 46569
A71: RAP1180 | B71: 37 | C71: CAP - 37. co-worker | D71: Swetha Kotturi | E71: Stefan Van Theemsche | J71: =IFERROR(VLOOKUP(A71,Directie!$A:$B,2,FALSE),"") -> CLP | K71: =IFERROR(VLOOKUP(A71,Directie!$A:$C,3,FALSE),"") -> SC | L71: 46174 | M71: 46569
A72: RAP1180 | B72: 20 | C72: CAP - 20. business partner | D72: Ivan Zelic | E72: Veera Raghavi Anusha Kakarlapudi | F72: Alan Eykmans | J72: =IFERROR(VLOOKUP(A72,Directie!$A:$B,2,FALSE),"") -> CLP | K72: =IFERROR(VLOOKUP(A72,Directie!$A:$C,3,FALSE),"") -> SC | L72: 46174 | M72: 46569
A73: RAP11875 | B73: 32 | C73: CAP - 32. finance | D73: Nithish Srivathsava Chittampally | E73: Stefan Van Theemsche | J73: =IFERROR(VLOOKUP(A73,Directie!$A:$B,2,FALSE),"") -> OKAY | K73: =IFERROR(VLOOKUP(A73,Directie!$A:$C,3,FALSE),"") -> Verkoop | L73: 46174 | M73: 46419
A74: RAP11875 | B74: 24 | C74: CAP - 24. data & analytics | J74: =IFERROR(VLOOKUP(A74,Directie!$A:$B,2,FALSE),"") -> OKAY | K74: =IFERROR(VLOOKUP(A74,Directie!$A:$C,3,FALSE),"") -> Verkoop | L74: 46174 | M74: 46419
A75: RAP11875 | B75: 20 | C75: CAP - 20. business partner | D75: Ivan Zelic | E75: Veera Raghavi Anusha Kakarlapudi | F75: Alan Eykmans | J75: =IFERROR(VLOOKUP(A75,Directie!$A:$B,2,FALSE),"") -> OKAY | K75: =IFERROR(VLOOKUP(A75,Directie!$A:$C,3,FALSE),"") -> Verkoop | L75: 46174 | M75: 46419
A76: RAP11875 | B76: 70 | C76: CAP - 70. food production | J76: =IFERROR(VLOOKUP(A76,Directie!$A:$B,2,FALSE),"") -> OKAY | K76: =IFERROR(VLOOKUP(A76,Directie!$A:$C,3,FALSE),"") -> Verkoop | L76: 46174 | M76: 46419
A77: RAP1195 | B77: 24 | C77: CAP - 24. data & analytics | J77: =IFERROR(VLOOKUP(A77,Directie!$A:$B,2,FALSE),"") -> CLP | K77: =IFERROR(VLOOKUP(A77,Directie!$A:$C,3,FALSE),"") -> SC | L77: 46174 | M77: 46569
A78: RAP1195 | B78: 47 | C78: CAP - 47. supply chain food | D78: Mustapha Guilmi | E78: Neelam Swamy | F78: Naga Venkata Vamshi Krishna Rao Kanaparthi | G78: SriHarsha Siddam | J78: =IFERROR(VLOOKUP(A78,Directie!$A:$B,2,FALSE),"") -> CLP | K78: =IFERROR(VLOOKUP(A78,Directie!$A:$C,3,FALSE),"") -> SC | L78: 46174 | M78: 46569
A79: RAP12073 | B79: 47 | C79: CAP - 47. supply chain food | D79: Mustapha Guilmi | E79: Neelam Swamy | F79: Naga Venkata Vamshi Krishna Rao Kanaparthi | G79: SriHarsha Siddam | J79: =IFERROR(VLOOKUP(A79,Directie!$A:$B,2,FALSE),"") -> CLP | K79: =IFERROR(VLOOKUP(A79,Directie!$A:$C,3,FALSE),"") -> Verkoop | L79: 46174 | M79: 46419
A80: RAP1214 | B80: 47 | C80: CAP - 47. supply chain food | D80: Mustapha Guilmi | E80: Neelam Swamy | F80: Naga Venkata Vamshi Krishna Rao Kanaparthi | G80: SriHarsha Siddam | J80: =IFERROR(VLOOKUP(A80,Directie!$A:$B,2,FALSE),"") -> CLP | K80: =IFERROR(VLOOKUP(A80,Directie!$A:$C,3,FALSE),"") -> SC | L80: 46174 | M80: 46569
A81: RAP1215 | B81: 47 | C81: CAP - 47. supply chain food | D81: Mustapha Guilmi | E81: Neelam Swamy | F81: Naga Venkata Vamshi Krishna Rao Kanaparthi | G81: SriHarsha Siddam | J81: =IFERROR(VLOOKUP(A81,Directie!$A:$B,2,FALSE),"") -> CLP | K81: =IFERROR(VLOOKUP(A81,Directie!$A:$C,3,FALSE),"") -> SC | L81: 46174 | M81: 46569
A82: RAP12293 | J82: =IFERROR(VLOOKUP(A82,Directie!$A:$B,2,FALSE),"") -> CLP | K82: =IFERROR(VLOOKUP(A82,Directie!$A:$C,3,FALSE),"") -> SC | L82: 46174 | M82: 46569
A83: RAP1233 | B83: 24 | C83: CAP - 24. data & analytics | J83: =IFERROR(VLOOKUP(A83,Directie!$A:$B,2,FALSE),"") -> CLP | K83: =IFERROR(VLOOKUP(A83,Directie!$A:$C,3,FALSE),"") -> SC | L83: 46174 | M83: 46569
A84: RAP1233 | B84: 47 | C84: CAP - 47. supply chain food | D84: Mustapha Guilmi | E84: Neelam Swamy | F84: Naga Venkata Vamshi Krishna Rao Kanaparthi | G84: SriHarsha Siddam | J84: =IFERROR(VLOOKUP(A84,Directie!$A:$B,2,FALSE),"") -> CLP | K84: =IFERROR(VLOOKUP(A84,Directie!$A:$C,3,FALSE),"") -> SC | L84: 46174 | M84: 46569
A85: RAP1237 | B85: 24 | C85: CAP - 24. data & analytics | J85: =IFERROR(VLOOKUP(A85,Directie!$A:$B,2,FALSE),"") -> CLP | K85: =IFERROR(VLOOKUP(A85,Directie!$A:$C,3,FALSE),"") -> SC | L85: 46174 | M85: 46569
A86: RAP1237 | B86: 47 | C86: CAP - 47. supply chain food | D86: Mustapha Guilmi | E86: Neelam Swamy | F86: Naga Venkata Vamshi Krishna Rao Kanaparthi | G86: SriHarsha Siddam | J86: =IFERROR(VLOOKUP(A86,Directie!$A:$B,2,FALSE),"") -> CLP | K86: =IFERROR(VLOOKUP(A86,Directie!$A:$C,3,FALSE),"") -> SC | L86: 46174 | M86: 46569
A87: RAP12414 | B87: 32 | C87: CAP - 32. finance | D87: Nithish Srivathsava Chittampally | E87: Stefan Van Theemsche | J87: =IFERROR(VLOOKUP(A87,Directie!$A:$B,2,FALSE),"") -> CLP | K87: =IFERROR(VLOOKUP(A87,Directie!$A:$C,3,FALSE),"") -> Verkoop | L87: 46174 | M87: 46419
A88: RAP12414 | B88: 24 | C88: CAP - 24. data & analytics | J88: =IFERROR(VLOOKUP(A88,Directie!$A:$B,2,FALSE),"") -> CLP | K88: =IFERROR(VLOOKUP(A88,Directie!$A:$C,3,FALSE),"") -> Verkoop | L88: 46174 | M88: 46419
A89: RAP12414 | B89: 18 | C89: CAP - 18. customer | D89: Dimitri Vanlinthout | F89: Dimitri Vanlinthout | G89: Kevin Kollin Mathew | H89: Ajay Mannepalli | I89: Dona Eliza Joseph | J89: =IFERROR(VLOOKUP(A89,Directie!$A:$B,2,FALSE),"") -> CLP | K89: =IFERROR(VLOOKUP(A89,Directie!$A:$C,3,FALSE),"") -> Verkoop | L89: 46174 | M89: 46419
A90: RAP12414 | B90: 44 | C90: CAP - 44. Store Sales Food | J90: =IFERROR(VLOOKUP(A90,Directie!$A:$B,2,FALSE),"") -> CLP | K90: =IFERROR(VLOOKUP(A90,Directie!$A:$C,3,FALSE),"") -> Verkoop | L90: 46174 | M90: 46419
A91: RAP12414 | B91: 71 | C91: CAP - 71. B2C sales food | D91: Christiaan Fosselle | J91: =IFERROR(VLOOKUP(A91,Directie!$A:$B,2,FALSE),"") -> CLP | K91: =IFERROR(VLOOKUP(A91,Directie!$A:$C,3,FALSE),"") -> Verkoop | L91: 46174 | M91: 46419
A92: RAP1242 | B92: 24 | C92: CAP - 24. data & analytics | J92: =IFERROR(VLOOKUP(A92,Directie!$A:$B,2,FALSE),"") -> CLP | K92: =IFERROR(VLOOKUP(A92,Directie!$A:$C,3,FALSE),"") -> SC | L92: 46174 | M92: 46569
A93: RAP1242 | B93: 47 | C93: CAP - 47. supply chain food | D93: Mustapha Guilmi | E93: Neelam Swamy | F93: Naga Venkata Vamshi Krishna Rao Kanaparthi | G93: SriHarsha Siddam | J93: =IFERROR(VLOOKUP(A93,Directie!$A:$B,2,FALSE),"") -> CLP | K93: =IFERROR(VLOOKUP(A93,Directie!$A:$C,3,FALSE),"") -> SC | L93: 46174 | M93: 46569
A94: RAP12436 | J94: =IFERROR(VLOOKUP(A94,Directie!$A:$B,2,FALSE),"") -> CLP | K94: =IFERROR(VLOOKUP(A94,Directie!$A:$C,3,FALSE),"") -> Verkoop | L94: 46174 | M94: 46419
A95: RAP12436 | B95: 24 | C95: CAP - 24. data & analytics | J95: =IFERROR(VLOOKUP(A95,Directie!$A:$B,2,FALSE),"") -> CLP | K95: =IFERROR(VLOOKUP(A95,Directie!$A:$C,3,FALSE),"") -> Verkoop | L95: 46174 | M95: 46419
A96: RAP12436 | B96: 18 | C96: CAP - 18. customer | D96: Dimitri Vanlinthout | F96: Dimitri Vanlinthout | G96: Kevin Kollin Mathew | H96: Ajay Mannepalli | I96: Dona Eliza Joseph | J96: =IFERROR(VLOOKUP(A96,Directie!$A:$B,2,FALSE),"") -> CLP | K96: =IFERROR(VLOOKUP(A96,Directie!$A:$C,3,FALSE),"") -> Verkoop | L96: 46174 | M96: 46419
A97: RAP12436 | B97: 44 | C97: CAP - 44. Store Sales Food | J97: =IFERROR(VLOOKUP(A97,Directie!$A:$B,2,FALSE),"") -> CLP | K97: =IFERROR(VLOOKUP(A97,Directie!$A:$C,3,FALSE),"") -> Verkoop | L97: 46174 | M97: 46419
A98: RAP12436 | B98: 71 | C98: CAP - 71. B2C sales food | D98: Christiaan Fosselle | J98: =IFERROR(VLOOKUP(A98,Directie!$A:$B,2,FALSE),"") -> CLP | K98: =IFERROR(VLOOKUP(A98,Directie!$A:$C,3,FALSE),"") -> Verkoop | L98: 46174 | M98: 46419
A99: RAP1249 | B99: 47 | C99: CAP - 47. supply chain food | D99: Mustapha Guilmi | E99: Neelam Swamy | F99: Naga Venkata Vamshi Krishna Rao Kanaparthi | G99: SriHarsha Siddam | J99: =IFERROR(VLOOKUP(A99,Directie!$A:$B,2,FALSE),"") -> CLP | K99: =IFERROR(VLOOKUP(A99,Directie!$A:$C,3,FALSE),"") -> SC | L99: 46174 | M99: 46569
A100: RAP12515 | B100: 24 | C100: CAP - 24. data & analytics | J100: =IFERROR(VLOOKUP(A100,Directie!$A:$B,2,FALSE),"") -> CLP | K100: =IFERROR(VLOOKUP(A100,Directie!$A:$C,3,FALSE),"") -> Verkoop | L100: 46174 | M100: 46419
...

Sheet Directie
A1: RAP | B1: OU | C1: Directie
A2: RAP10073 | B2: CLP | C2: Verkoop
A3: RAP18073 | B3: CLP | C3: Verkoop
A4: RAP18113 | B4: CLP | C4: Verkoop
A5: RAP18993 | B5: CLP | C5: Verkoop
A6: RAP21393 | B6: CLP | C6: Verkoop
A7: RAP21413 | B7: CLP | C7: Verkoop
A8: RAP23722 | B8: CLP | C8: Verkoop
A9: RAP24490 | B9: CLP | C9: Verkoop
A10: RAP2560 | B10: CLP | C10: Verkoop
A11: RAP25652 | B11: CLP | C11: Verkoop
A12: RAP25653 | B12: CLP | C12: Verkoop
... A2979: RAP32661 | B2979: 42. retail price food | C2979: CO
A2980: RAP32795 | B2980: Retail Services | C2980: CO | D2980: ! Retail Services is indication: was not filled in in orginal list
A2981: RAP32801 | B2981: 42. retail price food | C2981: CO
A2982: RAP32802 | B2982: Retail Services | C2982: CO | D2982: ! Retail Services is indication: was not filled in in orginal list
A2983: RAP33646 | B2983: 42. retail price food | C2983: CO
A2984: RAP33963 | B2984: Retail Services | C2984: CO
A2985: RAP33965 | B2985: Retail Services | C2985: CO
A2986: RAP33966 | B2986: Retail Services | C2986: CO
A2987: RAP33967 | B2987: Retail Services | C2987: CO
A2988: RAP30925 | B2988: 42. retail price food | C2988: CO
A2989: RAP29847 | B2989: 42. retail price food | C2989: CO
A2990: RAP23610 | B2990: 42. retail price food | C2990: CO
A2991: RAP24204 | B2991: 42. retail price food | C2991: CO
A2992: RAP24591 | B2992: 42. retail price food | C2992: CO
A2993: RAP24826 | B2993: 42. retail price food | C2993: CO
A2994: RAP25041 | B2994: 42. retail price food | C2994: CO
... A2996: RAP32101 | B2996: 42. retail price food | C2996: CO
A2997: RAP30500 | B2997: Retail Services | C2997: CO | D2997: ! Retail Services is indication: was not filled in in orginal list
A2998: RAP32806 | B2998: 42. retail price food | C2998: CO
A2999: RAP34029 | B2999: 42. retail price food | C2999: CO
A3000: RAP25852 | B3000: Retail Services | C3000: CO
A3001: RAP25885 | B3001: 42. retail price food | C3001: CO
A3002: RAP32273 | B3002: 42. retail price food | C3002: CO
A3003: RAP32567 | B3003: 42. retail price food | C3003: CO
A3004: RAP28082 | B3004: 42. retail price food | C3004: CO
A3005: RAP32976 | B3005: 42. retail price food | C3005: CO
A3006: RAP28883 | B3006: 42. retail price food | C3006: CO
A3007: RAP28957 | B3007: 42. retail price food | C3007: CO
A3008: RAP26698 | B3008: 42. retail price food | C3008: CO
A3009: RAP33771 | B3009: 42. retail price food | C3009: CO
... A3098: RAP31371 | B3098: 42. retail price food | C3098: CO
A3099: RAP34299 | B3099: Retail Services | C3099: CO | D3099: ! Retail Services is indication: was not filled in in orginal list
A3100: RAP31521 | B3100: 42. retail price food | C3100: CO
A3101: RAP30765 | B3101: Retail Services | C3101: CO
A3102: RAP31651 | B3102: 42. retail price food | C3102: CO
A3103: RAP31653 | B3103: 42. retail price food | C3103: CO
A3104: RAP31654 | B3104: 42. retail price food | C3104: CO
A3105: RAP31655 | B3105: 42. retail price food | C3105: CO
A3106: RAP3168 | B3106: 42. retail price food | C3106: CO
A3107: RAP31824 | B3107: 42. retail price food | C3107: CO
A3108: RAP31911 | B3108: 42. retail price food | C3108: CO
A3109: RAP31912 | B3109: 42. retail price food | C3109: CO
A3110: RAP31913 | B3110: 42. retail price food | C3110: CO
A3111: RAP30766 | B3111: Retail Services | C3111: CO
... A3178: RAP33016 | B3178: 42. retail price food | C3178: CO
A3179: RAP34210 | B3179: Retail Services | C3179: CO | D3179: ! Retail Services is indication: was not filled in in orginal list
A3180: RAP33026 | B3180: 42. retail price food | C3180: CO
A3181: RAP33028 | B3181: 42. retail price food | C3181: CO
A3182: RAP32862 | B3182: 42. retail price food | C3182: CO
A3183: RAP33049 | B3183: 42. retail price food | C3183: CO
A3184: RAP32863 | B3184: 42. retail price food | C3184: CO
A3185: RAP32864 | B3185: 42. retail price food | C3185: CO
A3186: RAP32865 | B3186: 42. retail price food | C3186: CO
A3187: RAP33150 | B3187: 42. retail price food | C3187: CO
A3188: RAP33151 | B3188: 42. retail price food | C3188: CO
A3189: RAP33184 | B3189: 42. retail price food | C3189: CO
A3190: RAP34211 | B3190: Retail Services | C3190: CO | D3190: ! Retail Services is indication: was not filled in in orginal list
A3191: RAP33036 | B3191: 42. retail price food | C3191: CO
A3192: RAP33209 | B3192: 42. retail price food | C3192: CO
A3193: RAP34278 | B3193: Retail Services | C3193: CO | D3193: ! Retail Services is indication: was not filled in in orginal list
A3194: RAP33233 | B3194: 42. retail price food | C3194: CO
A3195: RAP33237 | B3195: 42. retail price food | C3195: CO
A3196: RAP33305 | B3196: 42. retail price food | C3196: CO
A3197: RAP33308 | B3197: 42. retail price food | C3197: CO
A3198: RAP33312 | B3198: 42. retail price food | C3198: CO
A3199: RAP33349 | B3199: Retail Services | C3199: CO
A3200: RAP33381 | B3200: 42. retail price food | C3200: CO
A3201: RAP33382 | B3201: 42. retail price food | C3201: CO
A3202: RAP33386 | B3202: 42. retail price food | C3202: CO
A3203: RAP33430 | B3203: 42. retail price food | C3203: CO
A3204: RAP33441 | B3204: 42. retail price food | C3204: CO
A3205: RAP33207 | B3205: 42. retail price food | C3205: CO
... A3262: RAP34201 | B3262: Retail Services | C3262: CO
A3263: RAP34205 | B3263: Retail Services | C3263: CO | D3263: ! Retail Services is indication: was not filled in in orginal list
A3264: RAP34207 | B3264: Retail Services | C3264: CO | D3264: ! Retail Services is indication: was not filled in in orginal list
A3265: RAP27875 | B3265: 42. retail price food | C3265: CO
A3266: RAP32693 | B3266: 42. retail price food | C3266: CO
A3267: RAP34258 | B3267: Retail Services | C3267: CO | D3267: ! Retail Services is indication: was not filled in in orginal list
A3268: RAP34277 | B3268: Retail Services | C3268: CO | D3268: ! Retail Services is indication: was not filled in in orginal list
A3269: RAP33056 | B3269: 42. retail price food | C3269: CO
A3270: RAP34279 | B3270: Retail Services | C3270: CO | D3270: ! Retail Services is indication: was not filled in in orginal list
A3271: RAP33944 | B3271: 42. retail price food | C3271: CO
A3272: RAP34311 | B3272: Retail Services | C3272: CO | D3272: ! Retail Services is indication: was not filled in in orginal list
A3273: RAP34315 | B3273: Retail Services | C3273: CO | D3273: ! Retail Services is indication: was not filled in in orginal list
A3274: RAP34316 | B3274: Retail Services | C3274: CO | D3274: ! Retail Services is indication: was not filled in in orginal list
A3275: RAP34328 | B3275: Retail Services | C3275: CO | D3275: ! Retail Services is indication: was not filled in in orginal list
A3276: RAP34341 | B3276: Retail Services | C3276: CO | D3276: ! Retail Services is indication: was not filled in in orginal list
A3277: RAP34348 | B3277: Retail Services | C3277: CO | D3277: ! Retail Services is indication: was not filled in in orginal list
...

Sheet Caps per FRV iRap
A1: RAP10033 | B1: {=_xlfn.TEXTJOIN(", ", TRUE, IF('Caps per iRap'!$A$2:$A$19587=A1, 'Caps per iRap'!$B$2:$B$19587, ""))} -> 24, 16, 44, 40, 31, 71
A2: RAP10034 | B2: {=_xlfn.TEXTJOIN(", ", TRUE, IF('Caps per iRap'!$A$2:$A$19587=A2, 'Caps per iRap'!$B$2:$B$19587, ""))} -> 24, 16, 44, 40, 71
A3: RAP10073 | B3: {=_xlfn.TEXTJOIN(", ", TRUE, IF('Caps per iRap'!$A$2:$A$19587=A3, 'Caps per iRap'!$B$2:$B$19587, ""))} -> 24, 47, 30, 44, 40
A4: RAP1033 | B4: {=_xlfn.TEXTJOIN(", ", TRUE, IF('Caps per iRap'!$A$2:$A$19587=A4, 'Caps per iRap'!$B$2:$B$19587, ""))} -> 24, 47
A5: RAP1036 | B5: {=_xlfn.TEXTJOIN(", ", TRUE, IF('Caps per iRap'!$A$2:$A$19587=A5, 'Caps per iRap'!$B$2:$B$19587, ""))} -> 0, 47, 40
A6: RAP10413 | B6: {=_xlfn.TEXTJOIN(", ", TRUE, IF('Caps per iRap'!$A$2:$A$19587=A6, 'Caps per iRap'!$B$2:$B$19587, ""))} -> 44, 31, 37
A7: RAP10553 | B7: {=_xlfn.TEXTJOIN(", ", TRUE, IF('Caps per iRap'!$A$2:$A$19587=A7, 'Caps per iRap'!$B$2:$B$19587, ""))} -> 32, 24, 16, 18, 44, 40, 71
A8: RAP1091 | B8: {=_xlfn.TEXTJOIN(", ", TRUE, IF('Caps per iRap'!$A$2:$A$19587=A8, 'Caps per iRap'!$B$2:$B$19587, ""))} -> 24, 16, 47, 18, 40
A9: RAP10915 | B9: {=_xlfn.TEXTJOIN(", ", TRUE, IF('Caps per iRap'!$A$2:$A$19587=A9, 'Caps per iRap'!$B$2:$B$19587, ""))} -> 24, 47, 37
A10: RAP11014 | B10: {=_xlfn.TEXTJOIN(", ", TRUE, IF('Caps per iRap'!$A$2:$A$19587=A10, 'Caps per iRap'!$B$2:$B$19587, ""))} -> 0
A11: RAP11093 | B11: {=_xlfn.TEXTJOIN(", ", TRUE, IF('Caps per iRap'!$A$2:$A$19587=A11, 'Caps per iRap'!$B$2:$B$19587, ""))} -> 32, 18, 44, 31, 37
A12: RAP1164 | B12: {=_xlfn.TEXTJOIN(", ", TRUE, IF('Caps per iRap'!$A$2:$A$19587=A12, 'Caps per iRap'!$B$2:$B$19587, ""))} -> 24, 47, 40
... A2451: RAP6304 | B2451: {=_xlfn.TEXTJOIN(", ", TRUE, IF('Caps per iRap'!$A$2:$A$19587=A2451, 'Caps per iRap'!$B$2:$B$19587, ""))} -> 42, 30, 44, 40
A2452: RAP32686 | B2452: 24, 40, 71
A2453: RAP32711 | B2453: 0, 24, 44, 40, 71

Sheet Caps per iRap
A1: report_id | B1: CAP_NR
A2: RAP4932 | B2: 24
A3: RAP4932 | B3: 47
A4: RAP4932 | B4: 44
A5: RAP26851
A6: RAP26851 | B6: 16
A7: RAP26851 | B7: 47
A8: RAP26851 | B8: 44
A9: RAP26851 | B9: 40
A10: RAP26851 | B10: 71
A11: RAP26851 | B11: 20
A12: RAP3736 | B12: 24
A13: RAP3736 | B13: 47
A14: RAP3736 | B14: 40
A15: RAP3736 | B15: 37
A16: RAP7602 | B16: 32
A17: RAP7602 | B17: 24
... A36: RAP27288 | B36: 28
A37: RAP4820
A38: RAP4820 | B38: 30
A39: RAP28491 | B39: 24
A40: RAP28491 | B40: 30
A41: RAP28491 | B41: 31
A42: RAP26790 | B42: 24
A43: RAP26790 | B43: 30
A44: RAP26790 | B44: 18
A45: RAP26790 | B45: 51
A46: RAP26790 | B46: 44
A47: RAP26790 | B47: 40
A48: RAP26790 | B48: 31
A49: RAP30680
A50: RAP30680 | B50: 24
A51: RAP30680 | B51: 47
A52: RAP30680 | B52: 44
A53: RAP30680 | B53: 40
A54: RAP30680 | B54: 31
A55: RAP30680 | B55: 71
A56: RAP31322 | B56: 32
A57: RAP31322 | B57: 24
A58: RAP31322 | B58: 44
A59: RAP31322 | B59: 31
A60: RAP31322 | B60: 71
A61: RAP31776 | B61: 32
... A78: RAP33135 | B78: 20
A79: RAP33057
A80: RAP33057 | B80: 32
A81: RAP33057 | B81: 24
A82: RAP33057 | B82: 31
A83: RAP33057 | B83: 37
A84: RAP33057 | B84: 25
A85: RAP33910 | B85: 30
A86: RAP33910 | B86: 37
A87: RAP34236 | B87: 24
A88: RAP34236 | B88: 44
A89: RAP34236 | B89: 48
A90: RAP34236 | B90: 37
A91: RAP34236 | B91: 71
... A130: RAP30687 | B130: 40
A131: RAP31323
A132: RAP31323 | B132: 32
A133: RAP31323 | B133: 24
A134: RAP31323 | B134: 44
A135: RAP31323 | B135: 31
A136: RAP31323 | B136: 71
A137: RAP31854 | B137: 32
A138: RAP31854 | B138: 24
A139: RAP31854 | B139: 18
A140: RAP31854 | B140: 44
A141: RAP31854 | B141: 40
A142: RAP31854 | B142: 71
A143: RAP32305 | B143: 51
... A156: RAP33140 | B156: 20
A157: RAP33535
A158: RAP33535 | B158: 24
A159: RAP33535 | B159: 47
A160: RAP33535 | B160: 44
A161: RAP33535 | B161: 40
A162: RAP33535 | B162: 31
A163: RAP33919 | B163: 24
A164: RAP33919 | B164: 51
A165: RAP33919 | B165: 44
A166: RAP34235 | B166: 32
A167: RAP34235 | B167: 24
A168: RAP34235 | B168: 44
A169: RAP34235 | B169: 37
... A174: RAP33713 | B174: 43
A175: RAP27625
A176: RAP27625 | B176: 30
A177: RAP27625 | B177: 37
A178: RAP24409 | B178: 24
A179: RAP24409 | B179: 30
A180: RAP24409 | B180: 44
A181: RAP24409 | B181: 40
A182: RAP24409 | B182: 31
A183: RAP24409 | B183: 37
A184: RAP24409 | B184: 71
A185: RAP29767
A186: RAP29767 | B186: 24
A187: RAP29767 | B187: 30
A188: RAP29767 | B188: 44
...

Sheet SABI_List
A1: CAPABILITY | B1: SABI_1 | C1: SABI_2 | D1: EDWH_1 | E1: EDWH_2 | F1: EDWH_3 | G1: EDWH_4
A2: CAP - 00. identity & culture
A3: CAP - 01. strategy definition
A4: CAP - 02. resource planning
A5: CAP - 03. risk
A6: CAP - 04. market watch
A7: CAP - 05. performance watch
A8: CAP - 06. business change
A9: CAP - 07. real estate | B9: Stefan Van Theemsche | D9: Naga Venkata Vamshi Krishna Rao Kanaparthi
A10: CAP - 08. sustainability
A11: CAP - 09. R&D & innovation
A12: CAP - 10. digitalisation
A13: CAP - 11. stakeholder relations governance & reputation
A14: CAP - 12. communication & collaboration
A15: CAP - 14. marketing promotion | B15: Dimitri Vanlinthout | D15: Dimitri Vanlinthout | E15: Kevin Kollin Mathew | F15: Ajay Mannepalli | G15: Dona Eliza Joseph
A16: CAP - 15. contact center | B16: Dimitri Vanlinthout | D16: Dimitri Vanlinthout
A17: CAP - 16. direct purchasing | B17: Ivan Zelic | C17: Veera Raghavi Anusha Kakarlapudi | D17: Alan Eykmans
A18: CAP - 17. customer offer | B18: Philippe Du Bois | C18: Vivek Padinhare Veedu
A19: CAP - 18. customer | B19: Dimitri Vanlinthout | D19: Dimitri Vanlinthout | E19: Kevin Kollin Mathew | F19: Ajay Mannepalli | G19: Dona Eliza Joseph
A20: CAP - 20. business partner | B20: Ivan Zelic | C20: Veera Raghavi Anusha Kakarlapudi | D20: Alan Eykmans
A21: CAP - 21. party
A22: CAP - 22. workplace
A23: CAP - 23. integrated knowledge & search
A24: CAP - 24. data & analytics
A25: CAP - 25. indirect purchasing & warehousing | C25: Stefan Van Theemsche | D25: Naga Venkata Vamshi Krishna Rao Kanaparthi
A26: CAP - 26. compliance
A27: CAP - 27. customer payments | B27: Nithish Srivathsava Chittampally | C27: Stefan Van Theemsche
A28: CAP - 28. strategic & tactical planning
A29: CAP - 29. service & process
A30: CAP - 30. it | B30: Nithish Srivathsava Chittampally | C30: Stefan Van Theemsche
A31: CAP - 31. Infrastructure | B31: Stefan Van Theemsche | D31: Naga Venkata Vamshi Krishna Rao Kanaparthi
A32: CAP - 32. finance | B32: Nithish Srivathsava Chittampally | C32: Stefan Van Theemsche
A33: CAP - 35. Partnership & Organisation
A34: CAP - 36. Learning Solutions
A35: CAP - 37. co-worker | B35: Swetha Kotturi | C35: Stefan Van Theemsche
A36: CAP - 39. B2B foodservices | D36: Swapna Sarit Mallick
A37: CAP - 40. Retail Product Information | D37: Alan Eykmans
A38: CAP - 41. Contribution Food
A39: CAP - 42. Retail Price Food | B39: Philippe Du Bois
A40: CAP - 43. Logistic Workforce Food
A41: CAP - 44. Store Sales Food
A42: CAP - 45. sales forecasting food
A43: CAP - 47. supply chain food | B43: Mustapha Guilmi | C43: Neelam Swamy | D43: Naga Venkata Vamshi Krishna Rao Kanaparthi | E43: SriHarsha Siddam
A44: CAP - 48. B2B sales food | B44: Madhumitha Saravanan | D44: Thomas Villers | E44: Christiaan Fosselle
A45: CAP - 49. product development & quality
A46: CAP - 50. B2C e-commerce food | D46: Simon Desmet
A47: CAP - 51. nonfood retail
A48: CAP - 53. business transactions standards
A49: CAP - 56. store workforce food
A50: CAP - 57. servicing support
A51: CAP - 59. media
A52: CAP - 60. public relations
A53: CAP - 62. personal assistant supporting services
A54: CAP - 63. personal shopping assistance
A55: CAP - 65. pers. assistant partnership ops
A56: CAP - 66. personal assistant identity
A57: CAP - 67. product & recipe services | D57: Alan Eykmans
A58: CAP - 68. personal assistant digital channel
A59: CAP - 70. food production
A60: CAP - 71. B2C sales food | B60: Christiaan Fosselle
A61: CAP - 72. B2B customer relationship & interactions
A62: CAP - 73. import
A63: CAP - 81. mobility retail
A64: CAP - 82. colruyt group energy

Sheet Sheet1
A3: Row Labels | B3: Count of report_id | D3: Line of business | E3: Count of reports
A4: 0 | B4: 50 | D4: Colruyt Laagste Prijzen | E4: 718
A5: 12. communication & collaboration | B5: 1 | D5: Retail Partners Colruyt Group | E5: 433
A6: 16. direct purchasing | B6: 186 | D6: 42. retail price food | E6: 245
A7: 17. customer offer | B7: 17 | D7: 16. direct purchasing | E7: 186
A8: 18. customer | B8: 4 | D8: OKay | E8: 125
A9: 25. indirect purchasing & warehousing | B9: 4 | D9: #N/A | E9: 100
A10: 32. finance | B10: 12 | D10: CLP Supply Chain | E10: 64
A11: 37. co-worker | B11: 61 | D11: 37. co-worker | E11: 61
A12: 39. B2B foodservice | B12: 13 | D12: Bio-Planet | E12: 60
A13: 40. retail product information | B13: 3 | D13: Collect & Go | E13: 56
A14: 41. contribution food | B14: 30 | D14: Retail Services | E14: 54
A15: 42. retail price food | B15: 245 | D15: blank | E15: 50
A16: 43. logistic workforce food | B16: 6 | D16: Finance | E16: 43
... A50: Grand Total | B50: 2453 | D50: Grand Total | E50: 2453

Sheet Unique Reports
A1: report_id | B1: OU | C1: Directie | D1: Capabilities | E1: Report Name | F1: Line of Business | G1: Report Description (EN) | H1: Report Description (NL)
A2: RAP10033 | B2: CLP | C2: SC | D2: =VLOOKUP(A2,'Caps per FRV iRap'!A:B,2,0) -> 24, 16, 44, 40, 31, 71 | E2: Verkoop fruit groenten artikel code besteller lopende vorige maand | F2: 16. direct purchasing | G2: Confidential | H2: INBOX 26 BO 1M lopende maande en vorige maand cijfers aankopers fruit en groenten per artikel. Omzet, stuks, BW en afval
A3: RAP10034 | B3: CLP | C3: SC | D3: =VLOOKUP(A3,'Caps per FRV iRap'!A:B,2,0) -> 24, 16, 44, 40, 71 | E3: Verkoop fruit groenten artikel code besteller gisteren | F3: 16. direct purchasing | G3: Confidential | H3: INBOX 27 BO 1D gisteren cijfers aankopers per artikel stuks, omzet, BW en afval
A4: RAP10073 | B4: CLP | C4: Verkoop | D4: =VLOOKUP(A4,'Caps per FRV iRap'!A:B,2,0) -> 24, 47, 30, 44, 40 | E4: Artikelen meer dan 100 dagen stock filiaal firma FD VP DV | F4: Colruyt Laagste Prijzen | G4: All items FD, DV and VP with more than 100 days of stock at company and branch level. Available stock, number of branches track, forecast, branch stock | H4: Alle artikelen FD, DV en VP met meer dan 100 dagen stock op firma- en filiaalniveau. Beschikbare stock, aantal filalen volgen, prognose, filiaalstock
A5: RAP1033 | B5: CLP | C5: SC | D5: =VLOOKUP(A5,'Caps per FRV iRap'!A:B,2,0) -> 24, 47 | E5: Lege stockageplaatsen per blok | F5: Colruyt Laagste Prijzen | G5: Confidential | H5: Per blok kunnen de vrije en bezette plaatsen in het magazijn opgevraagd worden.
A6: RAP1036 | B6: CLP | C6: SC | D6: =VLOOKUP(A6,'Caps per FRV iRap'!A:B,2,0) -> 0, 47, 40 | E6: Onvolledige paletten reserve blok R | F6: Colruyt Laagste Prijzen | G6: Confidential | H6: Dit rapport geeft een overzicht van de paletten die onvolledig zijn Selectie obv blok W of R, stocksoort F of B en soort plaats R of N. Een palet is onvolledig indien aantal SE &lt; U
A7: RAP10413 | B7: BIO | C7: CO | D7: =VLOOKUP(A7,'Caps per FRV iRap'!A:B,2,0) -> 44, 31, 37 | E7: REMOVAL on 01Oct2026_Koppen en voltijdsequivalenten per filiaal | F7: 37. co-worker | G7: Not Applicable | H7: !!Dit rapport verdwijnt op 1 okt 2026!! Link Power BI-rapport in rap10413 'tab Info'. HC en FTE per filiaal. Voor het volledige filiaal als opgesplitst voor BH'en en winkels.
A8: RAP10553 | B8: CLP | C8: Verkoop | D8: =VLOOKUP(A8,'Caps per FRV iRap'!A:B,2,0) -> 32, 24, 16, 18, 44, 40, 71 | E8: Verkopen horecawijnen per prospecteur | F8: Colruyt Laagste Prijzen | G8: Confidential | H8: Weergave van het aantal verkochte wijnen , per referentie , per klant, per maand gekoppeld aan een accountmanager CLP4P.
A9: RAP1091 | B9: CLP | C9: SC | D9: =VLOOKUP(A9,'Caps per FRV iRap'!A:B,2,0) -> 24, 16, 47, 18, 40 | E9: leveringen art leva in pallet | F9: Colruyt Laagste Prijzen | G9: Confidential | H9: geeft het leveringen art leva in pal afhaling
A10: RAP10915 | B10: CLP | C10: SC | D10: =VLOOKUP(A10,'Caps per FRV iRap'!A:B,2,0) -> 24, 47, 37 | E10: overzicht aantal correcties per rondhaler per week | F10: Colruyt Laagste Prijzen | G10: Confidential | H10: overzicht aantal correcties per rondhaler per week
A11: RAP11014 | B11: CLP | C11: SC | D11: =VLOOKUP(A11,'Caps per FRV iRap'!A:B,2,0) -> 0 | E11: Aantal tellingen per afdeling _nultelling facturatie en wekelijkse | F11: Colruyt Laagste Prijzen | G11: Confidential | H11: Dit rapport geeft het aantal tellingen van vandaag per afdeling opgesplitst in nultellingen, tellingen tijdens facturatie en wekelijkse tellingen.
A12: RAP11093 | B12: CLP | C12: Verkoop | D12: =VLOOKUP(A12,'Caps per FRV iRap'!A:B,2,0) -> 32, 18, 44, 31, 37 | E12: Nieuwe factuurklanten binnen branche Horeca die geen Prof klant zijn | F12: Colruyt Laagste Prijzen | G12: Confidential | H12: Nieuwe factuurklanten in Colruytwinkels waarvan vastgesteld werden dat ze in de Horeco aktief zijn. Potentiële klanten voor Prof-tarief
A13: RAP1164 | B13: CLP | C13: SC | D13: =VLOOKUP(A13,'Caps per FRV iRap'!A:B,2,0) -> 24, 47, 40 | E13: art ZBH met datum nieuw 0 | F13: Colruyt Laagste Prijzen | G13: Confidential | H13: geeft de artikel van zelfbedieningsbeenhouwerijen
... A25: RAP1215 | B25: CLP | C25: SC | D25: =VLOOKUP(A25,'Caps per FRV iRap'!A:B,2,0) -> 47 | E25: overzicht ritten vertrokken vanuit magazijn | F25: Colruyt Laagste Prijzen | G25: Confidential | H25: Dit rapport geeft een overzicht van alle ritten vertrokken vanaf een bepaald magazijn
A26: RAP12293 | B26: CLP | C26: SC | D26: =VLOOKUP(A26,'Caps per FRV iRap'!A:B,2,0) | E26: #N/A | F26: #N/A | G26: #N/A | H26: #N/A
A27: RAP1233 | B27: CLP | C27: SC | D27: =VLOOKUP(A27,'Caps per FRV iRap'!A:B,2,0) -> 24, 47 | E27: Ritten voor chauffeur met algemene informatie | F27: Colruyt Laagste Prijzen | G27: Confidential | H27: Dit rapport geeft een overzicht van het dagparcours van een chauffeur met aanduiding van rij- en rusttijden
A28: RAP1237 | B28: CLP | C28: SC | D28: =VLOOKUP(A28,'Caps per FRV iRap'!A:B,2,0) -> 24, 47 | E28: Totaal overzicht retourvracht per magazijn | F28: Colruyt Laagste Prijzen | G28: Confidential | H28: Dit rapport geeft een overzicht van per magazijn over een bepaalde periode van het aantal tpe's die als terugvracht getransporteerd werden naar het betrokken magazijn.
A29: RAP12414 | B29: CLP | C29: Verkoop | D29: =VLOOKUP(A29,'Caps per FRV iRap'!A:B,2,0) -> 32, 24, 18, 44, 71 | E29: Omrekening profkorting kortingpercentage 5 | F29: Colruyt Laagste Prijzen | G29: Confidential | H29: In het rapport wordt de profkorting die een klant binnen een periode kreeg aan een bepaald profkortingpercentage omgerekend alsof deze klant recht had op 5% korting.
A30: RAP1242 | B30: CLP | C30: SC | D30: =VLOOKUP(A30,'Caps per FRV iRap'!A:B,2,0) -> 24, 47 | E30: verdienste specifieke transporteur over periode | F30: Colruyt Laagste Prijzen | G30: Confidential | H30: overzicht van de verdienste van een bepaalde transporteur voor een bepaalde periode.Opgelet: het ingeven van % is niet mogelijk als ingave bij chauffeur prompt
A31: RAP12436 | B31: CLP | C31: Verkoop | D31: =VLOOKUP(A31,'Caps per FRV iRap'!A:B,2,0) -> 0, 24, 18, 44, 71 | E31: Overzicht cbhids meer dan 5 keer herkend dmv extra kaart per regiomgr | F31: Corporate Marketing | G31: Confidential | H31: Overzicht van de cbhids die vorige week meer dan 5 keer herkend werden op eenzelfde dag
A32: RAP1249 | B32: CLP | C32: SC | D32: =VLOOKUP(A32,'Caps per FRV iRap'!A:B,2,0) -> 47 | E32: wie reed met oplegger | F32: Colruyt Laagste Prijzen | G32: Confidential | H32: geeft weer wie binnen een bepaalde periode met de gevraagde oplegger heeft gereden
A33: RAP12515 | B33: CLP | C33: Verkoop | D33: =VLOOKUP(A33,'Caps per FRV iRap'!A:B,2,0) -> 24, 47, 30, 5, 18, 44, 40, 71 | E33: Opvolgen horeca assortiment per maand per filiaal | F33: Colruyt Laagste Prijzen | G33: Confidential | H33: Vertrouwelijk
A34: RAP12517 | B34: CLP | C34: SC | D34: =VLOOKUP(A34,'Caps per FRV iRap'!A:B,2,0) -> 47, 37 | E34: Tussentijden borderels ONLINE | F34: Colruyt Laagste Prijzen | G34: Confidential | H34: De tijd tussen 2 borderels per rondhaler; PROMPTS: rondhaaldatum en rondhaalzones
A35: RAP12595 | B35: CLP | C35: SC | D35: =VLOOKUP(A35,'Caps per FRV iRap'!A:B,2,0) -> 24, 47, 40 | E35: niet getelde artikelen sinds | F35: Colruyt Laagste Prijzen | G35: Confidential | H35: Geeft de artikels per afdeling die niet meer geteld zijn sinds de ingegeven datum. Weergave van laatste telling door stockcontrole en bevoorrader, beschikbare stock en plmg.
A36: RAP1260 | B36: CLP | C36: SC | D36: =VLOOKUP(A36,'Caps per FRV iRap'!A:B,2,0) -> 47, 44, 37 | E36: Opzoeken rondhalers van een borderel NF en CS via bordnr | F36: Colruyt Laagste Prijzen | G36: Confidential | H36: Opzoeken rondhalers van een borderel NF en CS via borderelnummer
A37: RAP128 | B37: CLP | C37: Verkoop | D37: =VLOOKUP(A37,'Caps per FRV iRap'!A:B,2,0) -> 32, 18 | E37: Turnover Promisory Note Customers | F37: Finance | G37: Revenue Promessen | H37: Omzet Promessen
A38: RAP1283 | B38: CLP | C38: SC | D38: =VLOOKUP(A38,'Caps per FRV iRap'!A:B,2,0) -> 24, 47, 40, 37, 43 | E38: Overzicht rondhalers per pickingplaats | F38: 50. B2C e-commerce food | G38: Confidential | H38: Overzicht rondhalers die op een bepaalde plaats rondhaalden in de facturatie van gisteren
... A92: RAP21473 | B92: CLP | C92: AK | D92: =VLOOKUP(A92,'Caps per FRV iRap'!A:B,2,0) -> 32, 16, 30, 40, 20 | E92: Tarieflijst Aankoopdossier | F92: 16. direct purchasing | G92: Confidential | H92: overzicht BTP tarieven lijst per versie aankoopdossier
A93: RAP2151 | B93: OKAY | C93: Verkoop | D93: =VLOOKUP(A93,'Caps per FRV iRap'!A:B,2,0) | E93: #N/A | F93: #N/A | G93: #N/A | H93: #N/A
A94: RAP21613 | B94: OKAY | C94: Verkoop | D94: =VLOOKUP(A94,'Caps per FRV iRap'!A:B,2,0) -> 24, 47, 44, 40, 31, 71 | E94: Okay City Direct opvolging verkoop stock artikel filiaal regiomanager | F94: OKay | G94: Confidential | H94: In deze rapport vind je voor gevraagde artiklel en periode : verkoopcijfers en stock op filiaalniveau.
A95: RAP21973 | B95: CLP | C95: SC | D95: =VLOOKUP(A95,'Caps per FRV iRap'!A:B,2,0) -> 24, 47, 40 | E95: opvolging artikelen met stock zonder afmetingen of gewicht | F95: Colruyt Laagste Prijzen | G95: Confidential | H95: opvolging artikelen met stock zonder afmetingen of gewicht
A96: RAP22884 | B96: CLP | C96: Verkoop | D96: =VLOOKUP(A96,'Caps per FRV iRap'!A:B,2,0) -> 0, 42, 24, 18, 44, 40, 31, 71 | E96: Omrekenen kasticket of factuur met geldige Cprijzen en alle kortingen | F96: Colruyt Laagste Prijzen | G96: Confidential | H96: Om op basis van aankoopdatum, filiaalnr en kasticketnummer, het kasticket te herrekenen naar de Cprijzen zoals van kracht op datum. (meer info in metadata, tab ''Omschrijving'')
A97: RAP22885 | B97: CLP | C97: SC | D97: =VLOOKUP(A97,'Caps per FRV iRap'!A:B,2,0) -> 24, 16, 47, 40 | E97: Artikels per afdeling waar geen bevoorrading op zit sinds een datum | F97: Colruyt Laagste Prijzen | G97: ? | H97: Geeft de artikels waar geen bevoorrading op zit sinds de opgegeven datum. Toont of het artikel geblokkeerd is, moeder/dochter is, de levertermijn, beschikbare en wachtstock.
A98: RAP22892 | B98: CLP | C98: SC | D98: =VLOOKUP(A98,'Caps per FRV iRap'!A:B,2,0) -> 0 | E98: Overzicht lege plaatsen per blok of gang nonfood en collishop | F98: Colruyt Laagste Prijzen | G98: ? | H98: Geeft een overzicht van alle lege plaatsen in een bepaalde blok of gang van de afdelingen nonfood en collishop. Blok is verplicht, gang optioneel.
A99: RAP22904 | B99: CLP | C99: SC | D99: =VLOOKUP(A99,'Caps per FRV iRap'!A:B,2,0) -> 24, 47, 44, 40, 45 | E99: Resultaat simulatie herbevoorrading aantal colli's per magazijn vandaa | F99: Colruyt Laagste Prijzen | G99: ? | H99: ?
A100: RAP22906 | B100: CLP | C100: SC | D100: =VLOOKUP(A100,'Caps per FRV iRap'!A:B,2,0) -> 0, 24, 47, 44, 40 | E100: Overzicht filiaal of en artikel op PARH | F100: 45. sales forecasting food | G100: Confidential | H100: Vertrouwelijk
A101: RAP22947 | B101: CLP | C101: SC | D101: =VLOOKUP(A101,'Caps per FRV iRap'!A:B,2,0) -> 24, 47, 44 | E101: Vullingsgraad transportplanning | F101: Colruyt Laagste Prijzen | G101: Confidential | H101: Rapport geeft gemiddelde vullingsgraad per dag van alle ritten in de automatische planning.
A102: RAP23039 | B102: CLP | C102: SC | D102: =VLOOKUP(A102,'Caps per FRV iRap'!A:B,2,0) -> 24, 16, 18, 40 | E102: controle receptie op leveranciernr | F102: Colruyt Laagste Prijzen | G102: ? | H102: Geeft recepties weer tss bepaalde periode van bepaalde leverancier
A103: RAP23057 | B103: RPCG | C103: RPCG | D103: =VLOOKUP(A103,'Caps per FRV iRap'!A:B,2,0) -> 24, 48 | E103: opzoeken fouten weekrapportage | F103: Retail Partners Colruyt Group | G103: Confidential | H103: opzoeken fouten weekrapportage
A104: RAP23066 | B104: CLP | C104: SC | D104: =VLOOKUP(A104,'Caps per FRV iRap'!A:B,2,0) -> 24, 47, 40 | E104: Palletten te verwerken in circuit voor acirca vandaag per artikel | F104: Colruyt Laagste Prijzen | G104: ? | H104: Geeft aantal palletten bestemd voor circuit voor de facturatie van vandaag per gang, dus zonder de palletbestellingen. Geeft aantal palletplaatsen en plaatsstock van deze ochtend.
A105: RAP23079 | B105: CLP | C105: SC | D105: =VLOOKUP(A105,'Caps per FRV iRap'!A:B,2,0) -> 0, 44, 40, 20 | E105: overzicht sscc kode alle artikelen per leverancier | F105: Colruyt Laagste Prijzen | G105: Confidential | H105: overzicht sscc kode alle artikelen per leverancier
... A200: RAP24836 | B200: CLP | C200: Verkoop | D200: =VLOOKUP(A200,'Caps per FRV iRap'!A:B,2,0) -> 24, 47, 44, 40 | E200: Overzicht van een reeksetiket en onderliggende artikels | F200: Colruyt Laagste Prijzen | G200: ? | H200: Overzicht van een reeksetiket en onderliggende artikels
A201: RAP24843 | B201: CLP | C201: SC | D201: =VLOOKUP(A201,'Caps per FRV iRap'!A:B,2,0) -> 32, 24, 30, 44, 31, 37 | E201: #N/A | F201: #N/A | G201: #N/A | H201: #N/A
A202: RAP24860 | B202: CLP | C202: SC | D202: =VLOOKUP(A202,'Caps per FRV iRap'!A:B,2,0) -> 0 | E202: opkuis van F en U stock | F202: Colruyt Laagste Prijzen | G202: ? | H202: Dit rapport toont alle F en U stock die moet verwijderd worden van acties die reeds opgestuurd zijn naar de winkels
A203: RAP24861 | B203: CLP | C203: SC | D203: =VLOOKUP(A203,'Caps per FRV iRap'!A:B,2,0) -> 0, 42, 40 | E203: stock acties nonfood action dropper | F203: Colruyt Laagste Prijzen | G203: ? | H203: Dit rapport geeft een overzicht van alle actie stock obv actiecode om de F(U) en U stock op te volgen van een actie
A204: RAP24899 | B204: CLP | C204: SC | D204: =VLOOKUP(A204,'Caps per FRV iRap'!A:B,2,0) | E204: #N/A | F204: #N/A | G204: #N/A | H204: #N/A
A205: RAP24913 | B205: Solucious | C205: Marketing | D205: =VLOOKUP(A205,'Caps per FRV iRap'!A:B,2,0) -> 32, 31, 28 | E205: Masterdata Service Purchase Orders and Services _ Workorders _ Werknrs | F205: Finance | G205: Confidential | H205: Doel : overzicht lopende bestellingen en services
A206: RAP24916 | B206: CLP | C206: SC | D206: =VLOOKUP(A206,'Caps per FRV iRap'!A:B,2,0) -> 32 | E206: Masterdata Services and Prices | F206: Finance | G206: Confidential | H206: Doel : overzicht alle types services en tarieven
A207: RAP24921 | B207: CLP | C207: Verkoop | D207: =VLOOKUP(A207,'Caps per FRV iRap'!A:B,2,0) -> 24, 30, 44, 40, 71 | E207: Verkoopsopvolging beenhouwerij | F207: Colruyt Laagste Prijzen | G207: Confidential | H207: verkoopsopvolging beenhouwerij omzet volume afdelingschef firmaniveau promotor
A208: RAP24959 | B208: CLP | C208: SC | D208: =VLOOKUP(A208,'Caps per FRV iRap'!A:B,2,0) -> 0, 47, 5, 18, 40, 20 | E208: Pallettensaldo per leverancier per DC indirecte ruil | F208: Colruyt Laagste Prijzen | G208: ? | H208: Pallettensaldo per leverancier per DC voor het type europallet
A209: RAP24968 | B209: CLP | C209: SC | D209: =VLOOKUP(A209,'Caps per FRV iRap'!A:B,2,0) -> 0 | E209: opzoeken palletbarcode nonfood op basis van plaats | F209: Colruyt Laagste Prijzen | G209: ? | H209: Stockcontrole zoekt op basis van plaats met dit rapport de palletbarcode op. Alleen met de palletbarcode kan stockcontrole een pallet F(U) stock sortie doen.
A210: RAP24970 | B210: RPCG | C210: RPCG | D210: =VLOOKUP(A210,'Caps per FRV iRap'!A:B,2,0) -> 24, 30, 48 | E210: Stockcorrecties uit facturatieverslagen | F210: Retail Partners Colruyt Group | G210: ? | H210: ?
A211: RAP24986 | B211: CLP | C211: Marketing | D211: =VLOOKUP(A211,'Caps per FRV iRap'!A:B,2,0) -> 47, 44, 40 | E211: Artikelen in assortiment van een filiaal | F211: Colruyt Laagste Prijzen | G211: ? | H211: Artikelen in assortiment van een filiaal. Enkel artikelen met automatische bevoorrading + spiegelfilialen
A212: RAP24992 | B212: OKAY | C212: AK | D212: =VLOOKUP(A212,'Caps per FRV iRap'!A:B,2,0) -> 24, 16, 18, 44, 40, 31, 71 | E212: evaluatie cijfers verkoop huidige tov vorige periode aankoop | F212: OKay | G212: Confidential | H212: vergelijking week huidig jaar tov vorig jaar per aankoper per leverancier
A213: RAP24994 | B213: CLP | C213: SC | D213: =VLOOKUP(A213,'Caps per FRV iRap'!A:B,2,0) -> 0, 16, 47, 18, 44, 40 | E213: verschil U en bestelfactor per leverancier | F213: Colruyt Laagste Prijzen | G213: ? | H213: Overzicht van alle artikelen van de opgevraagde leverancier met aanleveringsRCU, RCU, bestelfactor, EDI barcode en levergroep.
A214: RAP25026 | B214: CLP | C214: SC | D214: =VLOOKUP(A214,'Caps per FRV iRap'!A:B,2,0) | E214: #N/A | F214: #N/A | G214: #N/A | H214: #N/A
A215: RAP25037 | B215: RPCG | C215: RPCG | D215: =VLOOKUP(A215,'Caps per FRV iRap'!A:B,2,0) -> 32, 24, 44, 37 | E215: BTW Z_Report | F215: Retail Partners Colruyt Group | G215: ? | H215: BTW Z_Report
A216: RAP25041 | B216: 42. retail price food | C216: CO | D216: =VLOOKUP(A216,'Caps per FRV iRap'!A:B,2,0) -> 42, 24, 16, 30, 40 | E216: Overzicht prijs groenten fruit aankoper | F216: 42. retail price food | G216: Confidential | H216: Overzicht met de concurrentprijzen van de laatste week (2 weken en 3 maanden)
A217: RAP25061 | B217: CLP | C217: SC | D217: =VLOOKUP(A217,'Caps per FRV iRap'!A:B,2,0) -> 47, 40, 37 | E217: Overzicht tellingen bevoorraders per dag afdeling food | F217: Colruyt Laagste Prijzen | G217: ? | H217: Geeft de tellingen van de bevoorrader per afdeling op een bepaalde datum. Weergave van RCU, imputatiecode, aantal en personeelslid.
A218: RAP25105 | B218: OKAY | C218: Verkoop | D218: =VLOOKUP(A218,'Caps per FRV iRap'!A:B,2,0) -> 32, 24, 28 | E218: Overzicht punteringen vorige week voor projectleiders | F218: IT | G218: Confidential | H218: Rapport geeft je een overzicht van de punteringen voor de projecten van projectleiders BP&amp;S (functionele groepen P2B, P2C en THW) van vorige week.
A219: RAP25107 | B219: OKAY | C219: Verkoop | D219: =VLOOKUP(A219,'Caps per FRV iRap'!A:B,2,0) -> 24, 30, 44, 40, 71 | E219: Analyse verkopen en degustaties per filiaal | F219: Colruyt Laagste Prijzen | G219: Confidential | H219: Dit rapport geeft je een overzicht van enkele cijfers van een artikel dat werd gedegusteerd. En dit een maand voor de degustatie, de degustatie zelf en een maand na de degustatie.
A220: RAP25123 | B220: CLP | C220: SC | D220: =VLOOKUP(A220,'Caps per FRV iRap'!A:B,2,0) -> 0, 47, 40 | E220: te conditioneren stock voor action dropper | F220: Colruyt Laagste Prijzen | G220: ? | H220: het rapport toont wat er nog te conditioneren is voor de actiondropper dat op stock staat plus het aantal nodige blauwe bakken
A221: RAP25150 | B221: CLP | C221: SC | D221: =VLOOKUP(A221,'Caps per FRV iRap'!A:B,2,0) -> 0 | E221: MICF NAWI wijzigen artikelinfo over periode_Backup | F221: Colruyt Laagste Prijzen | G221: ? | H221: Rapport is de online tegenhanger van MICF NAWI. Het geeft een overzicht van alle artikel aanpassingen over een bepaalde periode, gesorteerd op datum of personeelsnr
A222: RAP25176 | B222: RPCG | C222: RPCG | D222: =VLOOKUP(A222,'Caps per FRV iRap'!A:B,2,0) -> 24, 44, 40, 48, 37, 71 | E222: BTW rapport detail artikel | F222: Retail Partners Colruyt Group | G222: Confidential | H222: Detail op artikelniveau van het BTWrapport voor een bepaald departement
A223: RAP25188 | B223: Co&Go | C223: RPCG | D223: =VLOOKUP(A223,'Caps per FRV iRap'!A:B,2,0) -> 24, 47, 44, 40 | E223: Optimale stocks COGO Londerzeel per subgroep herschikking rayon | F223: Collect & Go | G223: Confidential | H223: Vertrouwelijk
A224: RAP25217 | B224: CLP | C224: Verkoop | D224: =VLOOKUP(A224,'Caps per FRV iRap'!A:B,2,0) -> 24, 30, 44, 31, 71 | E224: Vlees en klantenaandeel per jaarweek per filiaal | F224: Colruyt Laagste Prijzen | G224: Confidential | H224: Dit rapport geeft de dagaandelen van de winkel en Bh weer als ook het aantal klanten dat vlees koopt in %.
A225: RAP25236 | B225: Solucious | C225: Marketing | D225: =VLOOKUP(A225,'Caps per FRV iRap'!A:B,2,0) -> 0, 32, 30, 28 | E225: Overzicht doorgerekende projwest kosten | F225: Finance | G225: Confidential | H225: Dit geeft een overzicht van alle kosten die door BP&amp;S doorgerekend worden naar een gekozen kostenplaatsen voor gekozen maanden.
A226: RAP25256 | B226: CLP | C226: Verkoop | D226: =VLOOKUP(A226,'Caps per FRV iRap'!A:B,2,0) -> 32, 18 | E226: Aantal nieuwe profklanten per maand prospecteur activiteitscode | F226: Colruyt Laagste Prijzen | G226: Confidential | H226: Vertrouwelijk
... A263: RAP25614 | B263: OKAY | C263: Verkoop | D263: =VLOOKUP(A263,'Caps per FRV iRap'!A:B,2,0) -> 24, 30, 44, 31, 71 | E263: aantal klanten of unieke kasticketten per dag per uur OKay City | F263: OKay | G263: Not Applicable | H263: aantal klanten of unieke kasticketten per dag per uur OKay Compact BATCH
A264: RAP25618 | B264: OKAY | C264: Verkoop | D264: =VLOOKUP(A264,'Caps per FRV iRap'!A:B,2,0) | E264: #N/A | F264: #N/A | G264: #N/A | H264: #N/A
A265: RAP25625 | B265: OKAY | C265: Verkoop | D265: =VLOOKUP(A265,'Caps per FRV iRap'!A:B,2,0) | E265: #N/A | F265: #N/A | G265: #N/A | H265: #N/A
A266: RAP25641 | B266: CLP | C266: SC | D266: =VLOOKUP(A266,'Caps per FRV iRap'!A:B,2,0) -> 0, 42, 47, 40 | E266: #N/A | F266: #N/A | G266: #N/A | H266: #N/A
A267: RAP25642 | B267: CLP | C267: SC | D267: =VLOOKUP(A267,'Caps per FRV iRap'!A:B,2,0) -> 0 | E267: opzoeken van palletbarcode nonfood op basis van bakbarcode | F267: Colruyt Laagste Prijzen | G267: Not Applicable | H267: opzoeken van palletbarcode nonfood op basis van de laatste cijfers van een bakbarcode
A268: RAP25650 | B268: Co&Go | C268: RPCG | D268: =VLOOKUP(A268,'Caps per FRV iRap'!A:B,2,0) -> 24, 30, 50, 18, 44 | E268: Impact of store closure on other store CoGo | F268: Colruyt Laagste Prijzen | G268: Invloed sluiting winkel op collect and go andere winkel | H268: Het rapport berekent de impact op weekbasis van de sluiting van een afhaalpunt. Het afhaalpunt met impact én de periode is zelf te kiezen.
A269: RAP25652 | B269: CLP | C269: Verkoop | D269: =VLOOKUP(A269,'Caps per FRV iRap'!A:B,2,0) -> 24, 47, 44, 40, 71, 20 | E269: Opvolging receptie rechtstreekse levering REFI | F269: Colruyt Laagste Prijzen | G269: Not Applicable | H269: Doel van het rapport is om meer bewustwording te creëren rond het correct receptioneren van rechtstreekse leveringen.
A270: RAP25653 | B270: CLP | C270: Verkoop | D270: =VLOOKUP(A270,'Caps per FRV iRap'!A:B,2,0) -> 24, 47, 44, 40, 71 | E270: Opvolging receptie rechtstreekse levering REFI regiomanager | F270: Colruyt Laagste Prijzen | G270: Not Applicable | H270: Doel van het rapport is om meer bewustwording te creëren rond het correct receptioneren van rechtstreekse leveringen.
A271: RAP25655 | B271: CLP | C271: Verkoop | D271: =VLOOKUP(A271,'Caps per FRV iRap'!A:B,2,0) -> 32, 24, 18, 44, 40, 71 | E271: Overzicht verkopen vlees per filiaal profklanten | F271: Colruyt Laagste Prijzen | G271: This rapport shows the turnover in meet per store | H271: Dit rapport toont de omzet in vlees per profklant per winkel.
A272: RAP25685 | B272: OKAY | C272: Verkoop | D272: =VLOOKUP(A272,'Caps per FRV iRap'!A:B,2,0) -> 24, 30, 44, 40, 31, 71 | E272: opvolging OKay brood en bake off weekcijfers storemanager | F272: Colruyt Laagste Prijzen | G272: Not Applicable | H272: opvolging OKay brood en bake off weekcijfers storemanager batch of voor gekozen periode: volume, omzet, afval en BW per artikel.
A273: RAP25686 | B273: OKAY | C273: Verkoop | D273: =VLOOKUP(A273,'Caps per FRV iRap'!A:B,2,0) -> 24, 30, 44, 40, 31, 71 | E273: opvolging OKay brood en bake off weekcijfers regiomanager | F273: Colruyt Laagste Prijzen | G273: Not Applicable | H273: In deze rapport vind je per filiaal per RM voor vorige week voor brood en bake off : weekcijfers (volume, omzet, BW, afval) totaal per winkel en detail per artikel
A274: RAP25687 | B274: OKAY | C274: Verkoop | D274: =VLOOKUP(A274,'Caps per FRV iRap'!A:B,2,0) -> 24, 30, 44, 40, 31, 71 | E274: opvolging OKay brood en bake off weekcijfers online | F274: OKay | G274: Not Applicable | H274: In deze rapport vind je brood en bake off voor gevraagde periode cijfers per week. Voor alle winkels totaal en detail voor gevraagde winkel. cijfers: volume, omzet, afval en BW.
A275: RAP25693 | B275: RPCG | C275: RPCG | D275: =VLOOKUP(A275,'Caps per FRV iRap'!A:B,2,0) -> 16, 30, 18, 40 | E275: overzicht MF artikelen per leverancier per aankoper rpcg met WD en creatie datum | F275: Retail Partners Colruyt Group | G275: Not Applicable | H275: com47.647.291
A276: RAP25709 | B276: CLP | C276: SC | D276: =VLOOKUP(A276,'Caps per FRV iRap'!A:B,2,0) -> 0, 24, 31 | E276: Zoek ECO2 verbruikers | F276: Real estate | G276: Not Applicable | H276: Dit rapport laat toe adhv kernwoorden en locatie ECO2 verbruikers op te zoeken.
A277: RAP25720 | B277: OKAY | C277: Verkoop | D277: =VLOOKUP(A277,'Caps per FRV iRap'!A:B,2,0) -> 30, 37 | E277: overview linux servers | F277: IT | G277: query : device class = computer; sub class is containing "%LINUX%" and status = operational | H277: query : device class = computer; sub class is containing "%LINUX%" and status = operational
A278: RAP25728 | B278: CLP | C278: Verkoop | D278: =VLOOKUP(A278,'Caps per FRV iRap'!A:B,2,0) -> 32, 24, 30, 18, 40, 71 | E278: Articles vendu plus que x fois | F278: Colruyt Laagste Prijzen | G278: Articles vendu plus que x fois | H278: Artikelen meer dan x keer verkocht
... A307: RAP26051 | B307: CLP | C307: Marketing | D307: =VLOOKUP(A307,'Caps per FRV iRap'!A:B,2,0) -> 24, 16, 44, 40, 71 | E307: Boordtabel Productplan Keuze Assortiment 2 Periodes | F307: 17. customer offer | G307: Not Applicable | H307: Boordtabel Productplan Keuze Assortiment 2 Periodes
A308: RAP26070 | B308: CLP | C308: Marketing | D308: =VLOOKUP(A308,'Caps per FRV iRap'!A:B,2,0) | E308: #N/A | F308: #N/A | G308: #N/A | H308: #N/A
A309: RAP26073 | B309: CLP | C309: SC | D309: =VLOOKUP(A309,'Caps per FRV iRap'!A:B,2,0) -> 47, 44, 40 | E309: overzicht opvolging one touch facturatie | F309: Colruyt Laagste Prijzen | G309: Not Applicable | H309: Overzicht van onetouch bestelling
A310: RAP26081 | B310: Solucious | C310: Marketing | D310: =VLOOKUP(A310,'Caps per FRV iRap'!A:B,2,0) -> 24, 16, 47, 44, 40 | E310: leveringen stapelplaats aankostprijs | F310: 32. finance | G310: Not Applicable | H310: Leveringen door stapelplaats, aan één of meerdere Colruyt filialen, uitgesplitst per eigen merk / nationaal merk, gevalideerd aan de historische kostprijs.
A311: RAP26094 | B311: OKAY | C311: AK | D311: =VLOOKUP(A311,'Caps per FRV iRap'!A:B,2,0) -> 24, 44, 40, 71 | E311: Ranking Productgroep | F311: 17. customer offer | G311: Not Applicable | H311: Ranking Productgroep
A312: RAP26096 | B312: BIO | C312: Verkoop | D312: =VLOOKUP(A312,'Caps per FRV iRap'!A:B,2,0) -> 24, 30, 44, 40, 37, 71 | E312: Resultaat actie artikel voor CLP filialen vr 1 of meerdere dagen | F312: Colruyt Laagste Prijzen | G312: Not Applicable | H312: Dit rapport geeft het resultaat weer van de verkoopcijfers en aantal stuk van een artikel dat werd gedegusteerd tijdens een bepaalde periode. Enkel CLP
A313: RAP26118 | B313: OKAY | C313: Verkoop | D313: =VLOOKUP(A313,'Caps per FRV iRap'!A:B,2,0) -> 0, 24, 30, 44, 31, 71 | E313: procent kasticketten omzet okay | F313: Corporate OU | G313: procent kasticketten omzet | H313: procent kasticketten omzet
A314: RAP26121 | B314: OKAY | C314: Verkoop | D314: =VLOOKUP(A314,'Caps per FRV iRap'!A:B,2,0) -> 0, 24, 30, 18, 44, 31, 71 | E314: procent omzet kasticketten rm okay | F314: Corporate OU | G314: procent omzet kasticketten rm okay | H314: procent omzet kasticketten rm okay
A315: RAP26127 | B315: Solucious | C315: Marketing | D315: =VLOOKUP(A315,'Caps per FRV iRap'!A:B,2,0) -> 39 | E315: Leveringen per leveringsdag per hub en depot | F315: 39. B2B foodservice | G315: Not Applicable | H315: Zakencijfer geleverd, tonnage, aantal klanten en aantal ritten per dag per hub per depot
A316: RAP26136 | B316: CLP | C316: SC | D316: =VLOOKUP(A316,'Caps per FRV iRap'!A:B,2,0) -> 24, 37, 43 | E316: Overzicht gewerkte uren interim | F316: Colruyt Laagste Prijzen | G316: Not Applicable | H316: Dit rapport geeft een overzicht van alle uren gepunteerd op taken door interims. Packinterims worden apart vermeld in het rapport.
A317: RAP26146 | B317: Co&Go | C317: RPCG | D317: =VLOOKUP(A317,'Caps per FRV iRap'!A:B,2,0) -> 24, 30, 44, 71 | E317: Collection period COGO number of customers per quarter | F317: Collect & Go | G317: Not Applicable | H317: Vertoont het aantal afhalingen per kwartier met een prompt op filiaalnr(s) en verkoopdatum van ..... tot .....
A318: RAP26152 | B318: Solucious | C318: Marketing | D318: =VLOOKUP(A318,'Caps per FRV iRap'!A:B,2,0) -> 32, 20 | E318: FXX BOEKHD Boeking Euroconsultatie Uitgebreid | F318: Finance | G318: Not Applicable | H318: Euroconsultatie
A319: RAP26160 | B319: CLP | C319: SC | D319: =VLOOKUP(A319,'Caps per FRV iRap'!A:B,2,0) -> 24, 16, 47, 18, 40 | E319: Gereceptioneerde Goederen met Fnummer gonummer en commentaar receptie | F319: Colruyt Laagste Prijzen | G319: Not Applicable | H319: Na ingave van artikelnummer en datum kan je vanaf deze datum alle recepties zijn met hun go-nummer, Fnummer, commentaar receptie, bestelde en binnengenomen hoeveelheid
A320: RAP26167 | B320: OKAY | C320: Verkoop | D320: =VLOOKUP(A320,'Caps per FRV iRap'!A:B,2,0) -> 24, 47, 44, 40, 71 | E320: TELT met verplichte tellingen artikelen | F320: Technics | G320: TELT met verplichte tellingen artikelen | H320: TELT met verplichte tellingen artikelen
... A386: RAP27062 | B386: OKAY | C386: AK | D386: =VLOOKUP(A386,'Caps per FRV iRap'!A:B,2,0) -> 24, 30, 44, 40, 31, 71 | E386: batch rapport totaal cijfer cijfers OKay per groep afgelopen maand | F386: Colruyt Laagste Prijzen | G386: batch rapport totaal cijfer cijfers OKay per groep afgelopen 12 maand | H386: batch rapport totaal cijfer cijfers OKay per groep maand
A387: RAP27063 | B387: CLP | C387: Marketing | D387: =VLOOKUP(A387,'Caps per FRV iRap'!A:B,2,0) | E387: #N/A | F387: #N/A | G387: #N/A | H387: #N/A
...
